datalinks/__init__.py
datalinks/api.py
datalinks/cli.py
datalinks/links.py
datalinks/loaders.py
datalinks/pipeline.py
datalinks-0.0.31.dist-info/METADATA
datalinks-0.0.31.dist-info/WHEEL
datalinks-0.0.31.dist-info/licenses/LICENSE
datalinks-0.0.31.dist-info/RECORD
