Metadata-Version: 2.4
Name: datalinks
Version: 0.0.31
Summary: Base package to build indexing scripts for DataLinks
Project-URL: Homepage, https://datalinks.com
Author-email: Rui Lopes <rui.lopes@datasetlinks.com>, Francisco Ferreira <francisco@datasetlinks.com>, Andrzej Grzesik <ags@datasetlinks.com>, Rui Valente <rui.valente@datasetlinks.com>
License-File: LICENSE
Classifier: License :: OSI Approved :: MIT License
Classifier: Operating System :: OS Independent
Classifier: Programming Language :: Python :: 3
Requires-Python: >=3.11
Requires-Dist: caseutil==0.7.1
Requires-Dist: pytest==8.3.4
Requires-Dist: python-dotenv>=1.0.1
Requires-Dist: requests>=2.32
Requires-Dist: tox>=4.19
